rasengan/__init__.py
rasengan/main.py
rasengan/ssllabsscanner.py
rasengan-0.2.6.dist-info/DESCRIPTION.rst
rasengan-0.2.6.dist-info/METADATA
rasengan-0.2.6.dist-info/RECORD
rasengan-0.2.6.dist-info/WHEEL
rasengan-0.2.6.dist-info/entry_points.txt
rasengan-0.2.6.dist-info/metadata.json
rasengan-0.2.6.dist-info/top_level.txt
