Metadata-Version: 2.0
Name: rasengan
Version: 0.2.6
Summary: 
Home-page: https://github.com/apsl/rasengan
Author: Edu Herraiz
Author-email: eherraiz@apsl.net
License: GPLv3
Platform: UNKNOWN
Requires-Python: >=3.4
Requires-Dist: PyYAML (==3.12)
Requires-Dist: click (==6.7)
Requires-Dist: colorlog (==3.1.0)
Requires-Dist: dnspython (==1.15.0)
Requires-Dist: pyOpenSSL (==17.5.0)
Requires-Dist: requests (==2.18.4)
